optic_django_middleware/__init__.py
optic_django_middleware/apps.py
optic_django_middleware/container.py
optic_django_middleware/manager.py
optic_django_middleware/middleware.py
optic_django_middleware/serializers.py
optic_django_middleware-0.1.2.dist-info/WHEEL
optic_django_middleware-0.1.2.dist-info/METADATA
optic_django_middleware-0.1.2.dist-info/RECORD
