Metadata-Version: 2.1
Name: optic-django-middleware
Version: 0.1.2
Summary: Django Middleware for optic
Home-page: https://github.com/silentninja/optic-python
License: MIT
Keywords: swagger,optic,sdk,api,django,middleware
Author: Mukesh
Author-email: mmukesh95@hotmail.com
Requires-Python: >=3.7,<4.0
Classifier: Development Status :: 3 - Alpha
Classifier: Environment :: Web Environment
Classifier: Framework :: Django
Classifier: Framework :: Django :: 3.2
Classifier: Intended Audience :: Developers
Classifier: License :: OSI Approved :: MIT License
Classifier: Operating System :: OS Independent
Classifier: Programming Language :: Python :: 3
Classifier: Programming Language :: Python :: 3.7
Classifier: Programming Language :: Python :: 3.8
Classifier: Programming Language :: Python :: 3.9
Classifier: Topic :: Internet :: WWW/HTTP
Classifier: Topic :: Software Development :: Documentation
Classifier: Topic :: Software Development :: Libraries :: Python Modules
Provides-Extra: test
Requires-Dist: Django (>=3.2.4,<4.0.0)
Requires-Dist: freezegun (>=1.1.0,<2.0.0); extra == "test"
Requires-Dist: kubi-ecs-logger (>=0.1.0,<0.2.0)
Requires-Dist: optic-sdk (>=0.1.0,<0.2.0)
Project-URL: Repository, https://github.com/silentninja/optic-python/frameworks/django/optic_django_middleware
